motionmount/__init__.py
motionmount/motionmount.py
motionmount/py.typed
python_motionmount-2.3.1.dist-info/LICENSE.txt
python_motionmount-2.3.1.dist-info/METADATA
python_motionmount-2.3.1.dist-info/WHEEL
python_motionmount-2.3.1.dist-info/top_level.txt
python_motionmount-2.3.1.dist-info/RECORD
