Metadata-Version: 2.2
Name: python-MotionMount
Version: 2.3.1
Summary: Control your SIGNATURE MotionMount TVM7675 Pro using Python
Home-page: https://github.com/vogelsproducts/python-MotionMount
Author: Jaakko Laiho
Author-email: j.laiho@vogels.com
Project-URL: Bug Tracker, https://github.com/vogelsproducts/python-MotionMount/issues
Project-URL: repository, https://github.com/vogelsproducts/python-MotionMount
Classifier: Programming Language :: Python :: 3
Classifier: License :: OSI Approved :: MIT License
Classifier: Operating System :: OS Independent
Requires-Python: >=3.6
License-File: LICENSE.txt
